{
  "$id": "https://github.com/data-fair/simple-directory/site-public",
  "x-exports": ["types", "stringify"],
  "title": "site-public",
  "type":"object",
  "additionalProperties":false,
  "required":[
    "theme",
    "logo",
    "authMode"
  ],
  "properties":{
    "theme": {
      "$ref": "https://github.com/data-fair/simple-directory/site#/definitions/theme"
    },
    "logo": {
      "$ref": "https://github.com/data-fair/simple-directory/site#/definitions/logo"
    },
    "authMode": {
      "$ref": "https://github.com/data-fair/simple-directory/site#/definitions/auth-mode"
    }
  }
}